dumper/__init__.py
Dumper-1.2.0.dist-info/LICENSE
Dumper-1.2.0.dist-info/METADATA
Dumper-1.2.0.dist-info/WHEEL
Dumper-1.2.0.dist-info/top_level.txt
Dumper-1.2.0.dist-info/RECORD
